{"id":4674,"name":"BossRushGameJam","updated_at":"2024-02-04T07:40:08.000000Z","soundtracks":[{"id":5136,"song_id":5149,"name":"Behind Ennemy Lines","is_licensed":false,"updated_at":"2024-02-04T07:30:30.000000Z"},{"id":5137,"song_id":300660,"name":"Heartscrape","is_licensed":false,"updated_at":"2024-02-04T07:34:01.000000Z"},{"id":5138,"song_id":5661,"name":"Beast Mode","is_licensed":false,"updated_at":"2024-02-04T07:35:27.000000Z"},{"id":5139,"song_id":189925,"name":"Outrun","is_licensed":false,"updated_at":"2024-02-04T07:39:26.000000Z"},{"id":5140,"song_id":189918,"name":"Invaders","is_licensed":false,"updated_at":"2024-02-04T07:39:39.000000Z"},{"id":5141,"song_id":189915,"name":"Monsterbreaks","is_licensed":false,"updated_at":"2024-02-04T07:40:08.000000Z"}]}